karp/auth/__init__.py
karp/auth/application/__init__.py
karp/auth/application/queries/__init__.py
karp/auth/application/queries/resources.py
karp/auth/domain/__init__.py
karp/auth/domain/auth_service.py
karp/auth/domain/entities/__init__.py
karp/auth/domain/entities/user.py
karp/auth/domain/errors.py
karp/auth/domain/value_objects/__init__.py
karp/auth/domain/value_objects/token.py
karp/auth/py.typed
karp/auth_infrastructure/__init__.py
karp/auth_infrastructure/py.typed
karp/auth_infrastructure/queries/__init__.py
karp/auth_infrastructure/queries/lex_resources.py
karp/auth_infrastructure/services/__init__.py
karp/auth_infrastructure/services/dummy_auth_service.py
karp/auth_infrastructure/services/jwt_auth_service.py
karp/cliapp/__init__.py
karp/cliapp/main.py
karp/cliapp/py.typed
karp/cliapp/subapps/__init__.py
karp/cliapp/subapps/database_subapp.py
karp/cliapp/subapps/entries_subapp.py
karp/cliapp/subapps/entry_repo_subapp.py
karp/cliapp/subapps/query_subapp.py
karp/cliapp/subapps/resource_subapp.py
karp/cliapp/typer_injector.py
karp/cliapp/utility.py
karp/command_bus/__init__.py
karp/command_bus/core.py
karp/foundation/__init__.py
karp/foundation/constraints.py
karp/foundation/entity.py
karp/foundation/environs_sqlalchemyurl.py
karp/foundation/errors.py
karp/foundation/events.py
karp/foundation/messagebus.py
karp/foundation/py.typed
karp/foundation/repository.py
karp/foundation/text_manipulations.py
karp/foundation/time.py
karp/foundation/unit_of_work.py
karp/foundation/value_objects/__init__.py
karp/foundation/value_objects/machine_name.py
karp/foundation/value_objects/permission_level.py
karp/karp_v6_api/__init__.py
karp/karp_v6_api/contrib/__init__.py
karp/karp_v6_api/contrib/matomo.py
karp/karp_v6_api/dependencies/__init__.py
karp/karp_v6_api/dependencies/auth_deps.py
karp/karp_v6_api/dependencies/db_deps.py
karp/karp_v6_api/dependencies/event_deps.py
karp/karp_v6_api/dependencies/fastapi_injector.py
karp/karp_v6_api/dependencies/lex_deps.py
karp_backend-6.2.0.dist-info/entry_points.txt
karp_backend-6.2.0.dist-info/WHEEL
karp_backend-6.2.0.dist-info/METADATA
karp_backend-6.2.0.dist-info/RECORD
