Metadata-Version: 2.1
Name: karp-backend
Version: 6.2.0
Summary: 
License: MIT
Author: Kristoffer Andersson
Author-email: kristoffer.andersson@gu.se
Requires-Python: >=3.10,<4.0
Classifier: License :: OSI Approved :: MIT License
Classifier: Programming Language :: Python :: 3
Classifier: Programming Language :: Python :: 3.10
Provides-Extra: mysql
Provides-Extra: sqlite
Requires-Dist: Deprecated (>=1.2.13,<2.0.0)
Requires-Dist: PyMySQL (>=1.0.2,<2.0.0); extra == "mysql"
Requires-Dist: TatSu (>=5.8.3,<6.0.0)
Requires-Dist: aiomysql (>=0.1.1,<0.2.0); extra == "mysql"
Requires-Dist: aiosqlite (>=0.17.0,<0.18.0); extra == "sqlite"
Requires-Dist: alembic (>=1.8.1,<2.0.0)
Requires-Dist: asgi-correlation-id (>=3.0.1,<4.0.0)
Requires-Dist: elasticsearch (>=6,<7)
Requires-Dist: elasticsearch-dsl (>=6,<7)
Requires-Dist: environs (>=9.3.4,<10.0.0)
Requires-Dist: fastapi (>=0.89,<0.90)
Requires-Dist: injector (>=0.20.1,<0.21.0)
Requires-Dist: json-streams (>=0.12.0,<0.13.0)
Requires-Dist: karp-lex-core (>=0.5.1)
Requires-Dist: mysqlclient (>=2.1.1,<3.0.0); extra == "mysql"
Requires-Dist: paradigmextract (>=0.1.1,<0.2.0)
Requires-Dist: pydantic (>=1.10.2,<2.0.0)
Requires-Dist: pyjwt[crypto] (>=2.6.0,<3.0.0)
Requires-Dist: python-dotenv (>=0.19.0,<0.20.0)
Requires-Dist: python-json-logger (>=2.0.4,<3.0.0)
Requires-Dist: regex (>=2022.8.17,<2023.0.0)
Requires-Dist: sb-json-tools (>=0.9.1,<0.10.0)
Requires-Dist: sqlalchemy (>=1.4.44,<2.0.0)
Requires-Dist: sqlalchemy-json (>=0.5.0,<0.6.0)
Requires-Dist: sqlalchemy-utils (>=0.38.3,<0.39.0)
Requires-Dist: tabulate (>=0.9.0,<0.10.0)
Requires-Dist: tenacity (>=8.0.1,<9.0.0)
Requires-Dist: tqdm (>=4.64.1,<5.0.0)
Requires-Dist: typer (>=0.7.0,<0.8.0)
Requires-Dist: ulid-py (>=1.1.0,<2.0.0)
Requires-Dist: urllib3 (>=1.26.13,<2.0.0)
Project-URL: Bug Tracker, https://github.com/spraakbanken/karp-backend/issues
